sierraecg/__init__.py
sierraecg/lib.py
sierraecg/lzw.py
sierraecg/py.typed
sierraecg/xli.py
sierraecg-0.4.0.dist-info/LICENSE.txt
sierraecg-0.4.0.dist-info/METADATA
sierraecg-0.4.0.dist-info/WHEEL
sierraecg-0.4.0.dist-info/top_level.txt
sierraecg-0.4.0.dist-info/RECORD
