Metadata-Version: 2.1
Name: sierraecg
Version: 0.4.0
Summary: Sierra ECG Tools for Python
Home-page: https://github.com/sixlettervariables/sierra-ecg-tools
Author: 
Author-email: Christopher Watford <christopher.watford@gmail.com>
License: Copyright (c) 2022 Christopher Watford <christopher.watford@gmail.com>
Project-URL: Homepage, https://github.com/sixlettervariables/sierra-ecg-tools
Keywords: ecg,sierraecg,xml
Classifier: License :: OSI Approved :: MIT License
Classifier: Programming Language :: Python
Classifier: Programming Language :: Python :: 3
Classifier: Programming Language :: Python :: 3 :: Only
Classifier: Programming Language :: Python :: 3.9
Classifier: Programming Language :: Python :: 3.10
Classifier: Programming Language :: Python :: 3.11
Classifier: Programming Language :: Python :: 3.12
Classifier: Programming Language :: Python :: 3.13
Requires-Python: >=3.9
License-File: LICENSE.txt
Requires-Dist: defusedxml
Requires-Dist: numpy
Provides-Extra: dev
Requires-Dist: tox; extra == "dev"
Requires-Dist: pytest; extra == "dev"
Requires-Dist: pytest-cov; extra == "dev"
Requires-Dist: mypy; extra == "dev"
Requires-Dist: flake8; extra == "dev"
Requires-Dist: flake8-bugbear; extra == "dev"
Requires-Dist: flake8-broken-line; extra == "dev"
Requires-Dist: flake8-comprehensions; extra == "dev"
Requires-Dist: pep8-naming; extra == "dev"
Requires-Dist: black; extra == "dev"
Requires-Dist: isort; extra == "dev"
Requires-Dist: pip-tools; extra == "dev"
Requires-Dist: bumpver; extra == "dev"
Requires-Dist: mkdocs-material; extra == "dev"
Requires-Dist: mkdocs-htmlproofer-plugin; extra == "dev"
Requires-Dist: mkdocstrings[python]; extra == "dev"
Requires-Dist: mkdocs-gen-files; extra == "dev"
Requires-Dist: mkdocs-literate-nav; extra == "dev"
